morph_extractor/__init__.py
morph_extractor/cli.py
morph_extractor/config.py
morph_extractor/json_utils.py
morph_extractor/lang_code.py
morph_extractor/morphology_extractor.py
morph_extractor/token_utils.py
morph_extractor/wiktionary_loader.py
morph_extractor-0.1.11.dist-info/LICENSE
morph_extractor-0.1.11.dist-info/METADATA
morph_extractor-0.1.11.dist-info/WHEEL
morph_extractor-0.1.11.dist-info/entry_points.txt
morph_extractor-0.1.11.dist-info/top_level.txt
morph_extractor-0.1.11.dist-info/RECORD
