Metadata-Version: 2.2
Name: morph_extractor
Version: 0.1.11
Summary: A library to extract morphological data using Wiktionary and AI fallback
Author-email: Deepak Singh <iamdeepaksingh100@gmail.com>
License: MIT License
Keywords: linguistics,morphology,wiktionary,AI
Classifier: Programming Language :: Python :: 3
Classifier: License :: OSI Approved :: MIT License
Classifier: Operating System :: OS Independent
Requires-Python: >=3.8
License-File: LICENSE
